pymetropolis/__init__.py
pymetropolis/__main__.py
pymetropolis/cli.py
pymetropolis/main.py
pymetropolis/schema.py
pymetropolis/metro_common/__init__.py
pymetropolis/metro_common/errors.py
pymetropolis/metro_common/io.py
pymetropolis/metro_common/logger.py
pymetropolis/metro_common/types.py
pymetropolis/metro_common/utils.py
pymetropolis/metro_demand/__init__.py
pymetropolis/metro_demand/departure_time/__init__.py
pymetropolis/metro_demand/departure_time/files.py
pymetropolis/metro_demand/departure_time/linear_schedule_utility.py
pymetropolis/metro_demand/modes/__init__.py
pymetropolis/metro_demand/modes/car_driver.py
pymetropolis/metro_demand/modes/files.py
pymetropolis/metro_demand/modes/outside_option.py
pymetropolis/metro_demand/modes/public_transit.py
pymetropolis/metro_demand/od_matrix/__init__.py
pymetropolis/metro_demand/od_matrix/common.py
pymetropolis/metro_demand/od_matrix/each.py
pymetropolis/metro_demand/od_matrix/file.py
pymetropolis/metro_demand/od_matrix/gravity.py
pymetropolis/metro_demand/population/__init__.py
pymetropolis/metro_demand/population/draws.py
pymetropolis/metro_demand/population/files.py
pymetropolis/metro_demand/population/generic.py
pymetropolis/metro_demand/zones/__init__.py
pymetropolis/metro_demand/zones/custom.py
pymetropolis/metro_demand/zones/file.py
pymetropolis/metro_demand/zones/iris.py
pymetropolis/metro_demand/zones/osm.py
pymetropolis/metro_network/__init__.py
pymetropolis/metro_network/road_network/__init__.py
pymetropolis/metro_network/road_network/capacities.py
pymetropolis/metro_network/road_network/circular.py
pymetropolis/metro_network/road_network/custom.py
pymetropolis/metro_network/road_network/files.py
pymetropolis/metro_network/road_network/osm.py
pymetropolis/metro_network/road_network/penalties.py
pymetropolis/metro_network/road_network/postprocess.py
pymetropolis/metro_network/road_network/routing.py
pymetropolis/metro_pipeline/__init__.py
pymetropolis/metro_pipeline/config.py
pymetropolis-0.2.0.dist-info/METADATA
pymetropolis-0.2.0.dist-info/WHEEL
pymetropolis-0.2.0.dist-info/entry_points.txt
pymetropolis-0.2.0.dist-info/top_level.txt
pymetropolis-0.2.0.dist-info/RECORD
