Metadata-Version: 2.4
Name: pymetropolis
Version: 0.2.0
Summary: Helper functions to generate, calibrate, run, and analyze METROPOLIS2 simulation instances
Author-email: Lucas Javaudin <lucas@lucasjavaudin.com>
License-Expression: GPL-3.0-or-later
Project-URL: Homepage, https://metropolis2.org
Project-URL: Documentation, https://docs.metropolis2.org
Project-URL: Repository, https://github.com/Metropolis2/pymetropolis
Project-URL: Issues, https://github.com/Metropolis2/pymetropolis/issues
Keywords: transport simulation,metropolis2
Classifier: Programming Language :: Python
Classifier: Programming Language :: Python :: 3
Requires-Python: >=3.12
Requires-Dist: geopandas>=1.1.1
Requires-Dist: isodate>=0.7.2
Requires-Dist: loguru>=0.7.3
Requires-Dist: matplotlib>=3.10.8
Requires-Dist: networkx>=3.5
Requires-Dist: numpy>=2.3.4
Requires-Dist: osmium>=4.2.0
Requires-Dist: polars>=1.35.1
Requires-Dist: pyarrow>=22.0.0
Requires-Dist: pyproj>=3.7.2
Requires-Dist: pyogrio>=0.11.1
Requires-Dist: requests>=2.32.5
Requires-Dist: shapely>=2.1.2
Requires-Dist: termcolor>=3.2.0
Requires-Dist: typer>=0.20.0
Requires-Dist: toml>=0.10.2
Requires-Dist: typeguard>=4.4.4
